<metadata>
 <document uri="file:///home/vicyos/fedora_34_personal_scripts/vicyos-fedora-personal-autoconfig-v2.sh" atime="1618878098266">
  <entry key="gedit-encoding" value="UTF-8"/>
  <entry key="gedit-spell-language" value="pt_BR"/>
  <entry key="gedit-position" value="4396"/>
 </document>
 <document uri="file:///home/vicyos/Documentos/GIT&#x25;20FOLDERS/fedora_34_personal_scripts/vicyos-fedora-personal-autoconfig-v2.sh" atime="1619222092893">
  <entry key="gedit-encoding" value="UTF-8"/>
  <entry key="gedit-spell-language" value="pt_BR"/>
  <entry key="gedit-position" value="5996"/>
 </document>
 <document uri="file:///home/vicyos/vicyos-WhiteSur-gtk-theme-backup/upall/git-v2.sh" atime="1618878182758">
  <entry key="gedit-position" value="0"/>
 </document>
 <document uri="file:///home/vicyos/.config/gedit/accels" atime="1619221840886">
  <entry key="gedit-position" value="0"/>
 </document>
 <document uri="file:///home/vicyos/Documentos/GIT&#x25;20FOLDERS/fedora_34_personal_scripts/android-build-environment-setup-fedora32/fedora.sh" atime="1619054641004">
  <entry key="gedit-position" value="0"/>
 </document>
 <document uri="file:///home/vicyos/.bashrc" atime="1618753422377">
  <entry key="gedit-encoding" value="UTF-8"/>
  <entry key="gedit-spell-language" value="pt_BR"/>
  <entry key="gedit-position" value="7101"/>
 </document>
 <document uri="file:///home/vicyos/Downloads/vicyos-elementary-os-personal-scripts-master/desktop-install-all-scripts-at-once.sh" atime="1618674048147">
  <entry key="gedit-encoding" value="UTF-8"/>
  <entry key="gedit-spell-language" value="pt_BR"/>
  <entry key="gedit-position" value="1967"/>
 </document>
 <document uri="file:///home/vicyos/fedora_34_personal_scripts/README.md" atime="1618674041920">
  <entry key="gedit-encoding" value="UTF-8"/>
  <entry key="gedit-spell-language" value="pt_BR"/>
  <entry key="gedit-position" value="0"/>
 </document>
 <document uri="file:///home/vicyos/Documentos/GIT&#x25;20FOLDERS/fedora_34_personal_scripts/install_big_sur-theme_only.sh" atime="1618927434845">
  <entry key="gedit-encoding" value="UTF-8"/>
  <entry key="gedit-spell-language" value="pt_BR"/>
  <entry key="gedit-position" value="1057"/>
 </document>
 <document uri="file:///home/vicyos/fedora_34_personal_scripts/laptop-vicyos-fedora-personal-autoconfig-v2.sh" atime="1618673282560">
  <entry key="gedit-encoding" value="UTF-8"/>
  <entry key="gedit-spell-language" value="pt_BR"/>
  <entry key="gedit-position" value="4204"/>
 </document>
 <document uri="file:///home/vicyos/flutter/dartdoc_options.yaml" atime="1619221848344">
  <entry key="gedit-position" value="77"/>
 </document>
</metadata>
